soql/__init__.py
soql/attributes.py
soql/loaders.py
soql/model.py
soql/model_registry.py
soql/nodes.py
soql/path_builder.py
soql/select.py
soql/utils.py
soql-1.2.0.dist-info/AUTHORS
soql-1.2.0.dist-info/LICENSE
soql-1.2.0.dist-info/METADATA
soql-1.2.0.dist-info/WHEEL
soql-1.2.0.dist-info/top_level.txt
soql-1.2.0.dist-info/zip-safe
soql-1.2.0.dist-info/RECORD
