Metadata-Version: 2.1
Name: soql
Version: 1.2.0
Summary: Models and query generator for Salesforce Object Query Language (SOQL)
Home-page: https://github.com/plangrid/soql
Author: Barak Alon
Author-email: barak.s.alon@gmail.com
License: MIT
Keywords: salesforce,soql,salesforce.com
Classifier: Intended Audience :: Developers
Classifier: License :: OSI Approved :: MIT License
Classifier: Operating System :: OS Independent
Classifier: Programming Language :: Python
Classifier: Programming Language :: Python :: 2
Classifier: Programming Language :: Python :: 2.7
Classifier: Programming Language :: Python :: 3
Classifier: Programming Language :: Python :: 3.4
Classifier: Programming Language :: Python :: 3.5
Classifier: Programming Language :: Python :: 3.6
Classifier: Topic :: Software Development :: Libraries :: Python Modules
License-File: LICENSE
License-File: AUTHORS
Requires-Dist: python-dateutil
Requires-Dist: six
